sqlcraft/__init__.py
sqlcraft/base.py
sqlcraft/behaviours.py
sqlcraft/command.py
sqlcraft/conn.py
sqlcraft/constants.py
sqlcraft/copy_.py
sqlcraft/delete.py
sqlcraft/errors.py
sqlcraft/funcs.py
sqlcraft/insert.py
sqlcraft/misc.py
sqlcraft/query.py
sqlcraft/update.py
sqlcraft-0.1.4.dist-info/LICENSE
sqlcraft-0.1.4.dist-info/METADATA
sqlcraft-0.1.4.dist-info/WHEEL
sqlcraft-0.1.4.dist-info/top_level.txt
sqlcraft-0.1.4.dist-info/RECORD
