Metadata-Version: 2.1
Name: sqlcraft
Version: 0.1.4
Summary: Easy way to write SQL queries
Author-email: Dmitrii Kononenko <dmitriy.sergeevitch@gmail.com>
License: MIT License
Project-URL: repository, https://github.com/Dmitry-k42/sqlcraft
Keywords: sql,query builder,PostgreSQL
Classifier: License :: OSI Approved :: MIT License
Classifier: Programming Language :: Python
Classifier: Programming Language :: Python :: 3
Requires-Python: >=3.7
License-File: LICENSE
Requires-Dist: psycopg2 (>=2.9.1)
Provides-Extra: dev
Requires-Dist: pytest ; extra == 'dev'
Requires-Dist: pytest-cov ; extra == 'dev'
Requires-Dist: python-dotenv ; extra == 'dev'
Requires-Dist: pylint ; extra == 'dev'
Requires-Dist: build ; extra == 'dev'
Requires-Dist: twine ; extra == 'dev'
